termact/__init__.py
termact-0.0.2.dist-info/LICENSE.txt
termact-0.0.2.dist-info/METADATA
termact-0.0.2.dist-info/WHEEL
termact-0.0.2.dist-info/top_level.txt
termact-0.0.2.dist-info/RECORD
