Metadata-Version: 2.1
Name: termact
Version: 0.0.2
Summary: Clear the terminal with termact.clear()
License: UNKNOWN
Platform: UNKNOWN
License-File: LICENSE.txt
Requires-Dist: importlib ; python_version == "2.6"
